emlclient/__init__.py
emlclient/emailclient.py
emlclient/imap_smtp_factory.py
emlclient-1.0.0.dist-info/METADATA
emlclient-1.0.0.dist-info/WHEEL
emlclient-1.0.0.dist-info/top_level.txt
emlclient-1.0.0.dist-info/RECORD
