Metadata-Version: 2.1
Name: emlclient
Version: 1.0.0
Summary: 一个简单易用的邮件客户端，支持发送和接收邮件，支持 QQ 邮箱、163邮箱等邮箱 
Home-page: https://github.com/linsuiyuan/email-client
Author: Linsuiyuan
Author-email: linsuiyuan@icloud.com
Classifier: Programming Language :: Python :: 3
Classifier: License :: OSI Approved :: MIT License
Classifier: Operating System :: OS Independent
Requires-Python: >=3.8
